fabricks/__init__.py
fabricks/api/__init__.py
fabricks/api/cdc/__init__.py
fabricks/api/cdc/nocdc.py
fabricks/api/cdc/scd1.py
fabricks/api/cdc/scd2.py
fabricks/api/context.py
fabricks/api/core.py
fabricks/api/extenders.py
fabricks/api/log.py
fabricks/api/metastore/__init__.py
fabricks/api/metastore/database.py
fabricks/api/metastore/table.py
fabricks/api/metastore/view.py
fabricks/api/notebooks/__init__.py
fabricks/api/notebooks/cluster.py
fabricks/api/notebooks/deploy/__init__.py
fabricks/api/notebooks/deploy/fabricks.py
fabricks/api/notebooks/deploy/notebooks.py
fabricks/api/notebooks/initialize.py
fabricks/api/notebooks/optimize.py
fabricks/api/notebooks/process.py
fabricks/api/notebooks/run.py
fabricks/api/notebooks/terminate.py
fabricks/api/notebooks/vacuum.py
fabricks/api/parsers.py
fabricks/api/udfs.py
fabricks/api/utils.py
fabricks/cdc/__init__.py
fabricks/cdc/base/__init__.py
fabricks/cdc/base/cdc.py
fabricks/cdc/base/configurator.py
fabricks/cdc/base/generator.py
fabricks/cdc/base/merger.py
fabricks/cdc/base/processor.py
fabricks/cdc/base/types.py
fabricks/cdc/cdc.py
fabricks/cdc/nocdc.py
fabricks/cdc/scd.py
fabricks/cdc/scd1.py
fabricks/cdc/scd2.py
fabricks/cdc/templates/__init__.py
fabricks/cdc/templates/merge/scd1.sql.jinja
fabricks/cdc/templates/merge/scd2.sql.jinja
fabricks/cdc/templates/merge.sql.jinja
fabricks/cdc/templates/query/__init__.py
fabricks/cdc/templates/query/base.sql.jinja
fabricks/cdc/templates/query/context.sql.jinja
fabricks/cdc/templates/query/current.sql.jinja
fabricks/cdc/templates/query/deduplicate_hash.sql.jinja
fabricks/cdc/templates/query/deduplicate_key.sql.jinja
fabricks/cdc/templates/query/filter.sql.jinja
fabricks/cdc/templates/query/final.sql.jinja
fabricks/cdc/templates/query/hash.sql.jinja
fabricks/cdc/templates/query/nocdc.sql.jinja
fabricks/cdc/templates/query/rectify.sql.jinja
fabricks/cdc/templates/query/scd1.sql.jinja
fabricks/cdc/templates/query/scd2.sql.jinja
fabricks/cdc/templates/query.sql.jinja
fabricks-2024.7.1.5.dist-info/METADATA
fabricks-2024.7.1.5.dist-info/WHEEL
fabricks-2024.7.1.5.dist-info/RECORD
