Metadata-Version: 2.1
Name: fabricks
Version: 2024.7.1.5
Summary: 
Author: BMS DWH Team
Author-email: bi_support@bmsuisse.ch
Requires-Python: >=3.9,<4
Classifier: Programming Language :: Python :: 3
Classifier: Programming Language :: Python :: 3.9
Classifier: Programming Language :: Python :: 3.10
Classifier: Programming Language :: Python :: 3.11
Classifier: Programming Language :: Python :: 3.12
Requires-Dist: azure-data-tables (>=12.5.0,<13.0.0)
Requires-Dist: azure-identity (>=1.10.0)
Requires-Dist: azure-storage-blob (>=12.14.1)
Requires-Dist: azure-storage-queue (>=12.10.0,<13.0.0)
Requires-Dist: databricks-sdk (>=0.29.0)
Requires-Dist: jinja2 (>=2.11.3)
Requires-Dist: python-dotenv (>=1.0.1)
Requires-Dist: sqlglot (>=22.1.1)
